{
  "warp_kind": "botorch_warp",
  "output_transform_method": "yeo-johnson",
  "output_lambda": 1.4469047523564076,
  "output_sign_flip_applied": false,
  "fit_attempt_index": 0,
  "fit_attempt_label": "primary",
  "fit_attempt_count": 7,
  "fit_failed": false,
  "failed_attempts": [],
  "model_variant_name": "lin_matern32_add:power",
  "noise_est": 0.0022601067564685757,
  "len_min": NaN,
  "len_med": NaN,
  "warp_a": [
    0.036178517176751177,
    0.4369493408119723,
    1.253317472256477,
    3.027136950970369
  ],
  "warp_b": [
    0.3304976269479836,
    0.0007348323082718926,
    1.4029160777406913,
    8.568337989233541
  ],
  "function": "function_4",
  "d": 4,
  "n": 42,
  "kernel_mode": "lin_matern32_add",
  "acq_mode": "mace_pareto_pool",
  "ucb_betas": [
    0.5,
    0.75,
    1.0,
    1.25,
    1.5,
    1.75,
    2.0,
    2.25,
    2.5,
    2.75,
    3.0
  ],
  "n_sobol": 4096,
  "topk_per_acq": 32,
  "pool_size": 4608,
  "eligible_count": 4607,
  "dropped_duplicate_internal": 0,
  "dropped_duplicate_observed": 1,
  "pareto_size": 1,
  "selected_local_index": 3972,
  "selected_source_pool_index": 3973,
  "shadow_oldstyle_local_index": 4306,
  "sigma_quantile_used": 0.2,
  "sigma_threshold": 0.2651797334422543,
  "boundary_penalty_weight": 0.1,
  "boundary_penalty_min_dim": 4,
  "boundary_margin": 0.02,
  "selected_boundary_penalty": 0.0,
  "selected_exploration_score": 0.03527408362057652,
  "selected_strategy_name": "trust_region_ts",
  "selected_candidate_origin": "tr",
  "stagnation_flag": true,
  "stagnation_gain": 0.0926770964062591,
  "stagnation_threshold": 0.3292396749761516,
  "stagnation_scale": 16.46198374880758,
  "stagnation_window": 6,
  "trust_region_length": 0.35,
  "trust_region_restarts": 3,
  "best_y_raw": 0.7013049970924787,
  "best_y_transformed": 0.7998772040888138,
  "nn_min_observed": 0.022631815945699095,
  "nn_median_observed": 0.21777164676481134,
  "seed": 3001,
  "selection_mode": "robust_consensus",
  "n_seed_success": 5,
  "n_seed_fail": 0,
  "unique_suggestions": 5,
  "consensus_frequency": 1,
  "consensus_frequency_ratio": 0.2,
  "selected_portal_string": "0.460206-0.407745-0.385458-0.434045",
  "selected_seed": 3001,
  "fallback_used": false,
  "fit_attempt_distribution": {
    "primary": 5
  }
}