{
  "warp_kind": "botorch_warp",
  "output_transform_method": "yeo-johnson",
  "output_lambda": 1.758628004493194,
  "output_sign_flip_applied": false,
  "fit_attempt_index": 0,
  "fit_attempt_label": "primary",
  "fit_attempt_count": 7,
  "fit_failed": false,
  "failed_attempts": [],
  "model_variant_name": "lin_matern32_add:power",
  "noise_est": 0.10793422015430285,
  "len_min": NaN,
  "len_med": NaN,
  "warp_a": [
    4.005671793593737,
    1.3843431667972874
  ],
  "warp_b": [
    2.306715047277937,
    0.0001
  ],
  "function": "function_2",
  "d": 2,
  "n": 22,
  "kernel_mode": "lin_matern32_add",
  "acq_mode": "mace_pareto_pool",
  "ucb_betas": [
    0.5,
    0.75,
    1.0,
    1.25,
    1.5,
    1.75,
    2.0,
    2.25,
    2.5,
    2.75,
    3.0
  ],
  "n_sobol": 4096,
  "topk_per_acq": 32,
  "pool_size": 4608,
  "eligible_count": 4608,
  "dropped_duplicate_internal": 0,
  "dropped_duplicate_observed": 0,
  "pareto_size": 183,
  "selected_local_index": 3757,
  "selected_source_pool_index": 3757,
  "shadow_oldstyle_local_index": 3191,
  "sigma_quantile_used": 0.35,
  "sigma_threshold": 0.062072917336383114,
  "boundary_penalty_weight": 0.1,
  "boundary_penalty_min_dim": 4,
  "boundary_margin": 0.02,
  "selected_boundary_penalty": 0.0,
  "selected_exploration_score": 0.012592245843371938,
  "selected_strategy_name": "primary_pareto_sigma",
  "selected_candidate_origin": "tr",
  "stagnation_flag": false,
  "stagnation_gain": 0.040248706727148864,
  "stagnation_threshold": 0.008918903378441138,
  "stagnation_scale": 0.44594516892205693,
  "stagnation_window": 6,
  "trust_region_length": 0.0875,
  "trust_region_restarts": 1,
  "best_y_raw": 0.6514539224885927,
  "best_y_transformed": 0.8053285406508844,
  "nn_min_observed": 0.015477280510477318,
  "nn_median_observed": 0.07492988949141612,
  "seed": 1004,
  "selection_mode": "robust_consensus",
  "n_seed_success": 5,
  "n_seed_fail": 0,
  "unique_suggestions": 5,
  "consensus_frequency": 1,
  "consensus_frequency_ratio": 0.2,
  "selected_portal_string": "0.731405-0.855051",
  "selected_seed": 1004,
  "fallback_used": false,
  "fit_attempt_distribution": {
    "primary": 5
  }
}